strayfield_horep/__init__.py
strayfield_horep/strayfield.py
strayfield_horep-0.0.4.dist-info/LICENSE
strayfield_horep-0.0.4.dist-info/METADATA
strayfield_horep-0.0.4.dist-info/WHEEL
strayfield_horep-0.0.4.dist-info/top_level.txt
strayfield_horep-0.0.4.dist-info/RECORD
