Metadata-Version: 2.1
Name: strayfield_horep
Version: 0.0.4
Summary: A strayfield package for micromagnetics
Author-email: Hywel Normington <hywel.normington@strath.ac.uk>
Project-URL: Homepage, https://github.com/Horep/strayfield
Classifier: License :: OSI Approved :: MIT License
License-File: LICENSE
